sentianalib/__init__.py
sentianalib/dataprocessor.py
sentianalib/setup.py
sentianalib-1.0.0.dist-info/LICENSE
sentianalib-1.0.0.dist-info/METADATA
sentianalib-1.0.0.dist-info/WHEEL
sentianalib-1.0.0.dist-info/top_level.txt
sentianalib-1.0.0.dist-info/RECORD
