Metadata-Version: 2.1
Name: sentianalib
Version: 1.0.0
License-File: LICENSE
Requires-Dist: beautifulsoup4 >=4.12.3
Requires-Dist: textblob >=0.18.0
Requires-Dist: selenium >=4.18.1
Requires-Dist: webdriver-manager >=4.0.1
